setup.py
correios/__init__.py
correios/correios.py
correios/scraping.py
correios_api_py.egg-info/PKG-INFO
correios_api_py.egg-info/SOURCES.txt
correios_api_py.egg-info/dependency_links.txt
correios_api_py.egg-info/requires.txt
correios_api_py.egg-info/top_level.txt