Metadata-Version: 1.0
Name: correios-api-py
Version: 0.1.1
Summary: API Python para obter informacoes de encomendas/Sedex dos Correios.
Home-page: http://github.com/guilhermechapiewski/correios-api-py/
Author: Guilherme Chapiewski
Author-email: guilherme.chapiewski@gmail.com
License: Apache License 2.0
Keywords: correios brasil api
Platform: UNKNOWN
